README.md
setup.py
EarClipping/__init__.py
EarClipping/core.py
EarClipping.egg-info/PKG-INFO
EarClipping.egg-info/SOURCES.txt
EarClipping.egg-info/dependency_links.txt
EarClipping.egg-info/requires.txt
EarClipping.egg-info/top_level.txt