Metadata-Version: 2.1
Name: EarClipping
Version: 0.1.1
Summary: EarClipping
Home-page: https://github.com/bigpangl/EarClipping
Author: LHao
Author-email: bigpangl@163.com
License: UNKNOWN
Platform: UNKNOWN
